tft/artemis/__init__.py
tft/artemis/api/__init__.py
tft/artemis/api/about.html.j2
tft/artemis/api/dependencies.py
tft/artemis/api/environment.py
tft/artemis/api/errors.py
tft/artemis/api/middleware.py
tft/artemis/api/models/__init__.py
tft/artemis/api/models/v0_0_69.py
tft/artemis/api/models/v0_0_72.py
tft/artemis/api/routers/__init__.py
tft/artemis/api/routers/_cache.py.bak
tft/artemis/api/routers/_shelves.py.bak
tft/artemis/api/routers/common.py
tft/artemis/api/routers/v0_0_17.py
tft/artemis/api/routers/v0_0_18.py
tft/artemis/api/routers/v0_0_19.py
tft/artemis/api/routers/v0_0_20.py
tft/artemis/api/routers/v0_0_21.py
tft/artemis/api/routers/v0_0_24.py
tft/artemis/api/routers/v0_0_26.py
tft/artemis/api/routers/v0_0_27.py
tft/artemis/api/routers/v0_0_28.py
tft/artemis/api/routers/v0_0_32.py
tft/artemis/api/routers/v0_0_37.py
tft/artemis/api/routers/v0_0_38.py
tft/artemis/api/routers/v0_0_46.py
tft/artemis/api/routers/v0_0_47.py
tft/artemis/api/routers/v0_0_48.py
tft/artemis/api/routers/v0_0_53.py
tft/artemis/api/routers/v0_0_55.py
tft/artemis/api/routers/v0_0_56.py
tft/artemis/api/routers/v0_0_58.py
tft/artemis/api/routers/v0_0_67.py
tft/artemis/api/routers/v0_0_69.py
tft/artemis/api/routers/v0_0_70.py
tft/artemis/api/routers/v0_0_72.py
tft/artemis/api/routers/v0_0_73.py
tft/artemis/api/routers/v0_0_74.py
tft/artemis/cache.py
tft/artemis/context.py
tft/artemis/db.py
tft/artemis/dispatcher.py
tft/artemis/drivers/__init__.py
tft/artemis/drivers/aws.py
tft/artemis/drivers/azure.py
tft/artemis/drivers/beaker.py
tft/artemis/drivers/gcp.py
tft/artemis/drivers/hooks.py
tft/artemis/drivers/ibmcloudpower.py
tft/artemis/drivers/ibmcloudvpc.py
tft/artemis/drivers/localhost.py
tft/artemis/drivers/openstack.py
tft/artemis/drivers/rest.py
tft/artemis/environment.py
tft/artemis/guest.py
tft/artemis/knobs.py
tft/artemis/mailbox.py.bak
tft/artemis/metrics.py
tft/artemis/middleware.py
tft/artemis/profile.py
tft/artemis/py.typed
tft/artemis/routing_policies.py
tft_artemis-0.0.75.dist-info/METADATA
tft_artemis-0.0.75.dist-info/WHEEL
tft_artemis-0.0.75.dist-info/entry_points.txt
tft_artemis-0.0.75.dist-info/RECORD
