Metadata-Version: 2.1
Name: tft-artemis
Version: 0.0.75
Summary: Artemis is a machine provisioning service. Its goal is to provision a machine - using a set of preconfigured providers as backends - which would satisfy the given hardware and software requirements.
License: Apache-2.0
Author: Milos Prchlik
Author-email: mprchlik@redhat.com
Requires-Python: >=3.9.0,<3.10.0
Classifier: License :: OSI Approved :: Apache Software License
Classifier: Programming Language :: Python :: 3
Classifier: Programming Language :: Python :: 3.9
Provides-Extra: full
Requires-Dist: Pint (==0.18)
Requires-Dist: alembic (==1.8.1)
Requires-Dist: awscli (>=1.36.13) ; extra == "full"
Requires-Dist: azure-cli ; extra == "full"
Requires-Dist: beaker-client ; extra == "full"
Requires-Dist: click
Requires-Dist: dramatiq[rabbitmq] (==1.13.0)
Requires-Dist: fastapi
Requires-Dist: gluetool (>=2.5,<3.0)
Requires-Dist: google-cloud-compute ; extra == "full"
Requires-Dist: gunicorn
Requires-Dist: jinja2-ansible-filters
Requires-Dist: jq
Requires-Dist: jsonschema
Requires-Dist: pendulum (>=2.0,<3.0)
Requires-Dist: periodiq
Requires-Dist: prometheus-client (>=0.12.0,<0.13.0)
Requires-Dist: psycopg2
Requires-Dist: pyinstrument
Requires-Dist: pykickstart (>=3.58,<4.0)
Requires-Dist: python-glanceclient
Requires-Dist: python-novaclient
Requires-Dist: python-openstackclient (>=6.0.0,<7.0.0) ; extra == "full"
Requires-Dist: redis
Requires-Dist: sentry-sdk (>=2.18,<3.0)
Requires-Dist: setuptools
Requires-Dist: sqlalchemy-utils[encrypted]
Requires-Dist: sqlalchemy[mypy,postgresql,postgresql-psycopg]
Requires-Dist: stackprinter
Requires-Dist: starlette (==0.41.2)
Requires-Dist: typing-extensions
Requires-Dist: uvicorn
